[
  {
    "item_id": "T2_LEATHER",
    "city": "Fort Sterling",
    "quality": 1,
    "sell_price_min": 40,
    "sell_price_min_date": "2022-11-18T14:45:00",
    "sell_price_max": 48,
    "sell_price_max_date": "2022-11-18T14:45:00",
    "buy_price_min": 0,
    "buy_price_min_date": "0001-01-01T00:00:00",
    "buy_price_max": 0,
    "buy_price_max_date": "0001-01-01T00:00:00"
  },
  {
    "item_id": "T2_LEATHER",
    "city": "Martlock",
    "quality": 1,
    "sell_price_min": 45,
    "sell_price_min_date": "2022-11-18T09:40:00",
    "sell_price_max": 60,
    "sell_price_max_date": "2022-11-18T09:40:00",
    "buy_price_min": 43,
    "buy_price_min_date": "2022-11-18T09:45:00",
    "buy_price_max": 43,
    "buy_price_max_date": "2022-11-18T09:45:00"
  },
  {
    "item_id": "T3_HIDE",
    "city": "Fort Sterling",
    "quality": 1,
    "sell_price_min": 55,
    "sell_price_min_date": "2022-11-18T12:55:00",
    "sell_price_max": 68,
    "sell_price_max_date": "2022-11-18T12:55:00",
    "buy_price_min": 0,
    "buy_price_min_date": "0001-01-01T00:00:00",
    "buy_price_max": 0,
    "buy_price_max_date": "0001-01-01T00:00:00"
  },
  {
    "item_id": "T3_HIDE",
    "city": "Martlock",
    "quality": 1,
    "sell_price_min": 66,
    "sell_price_min_date": "2022-11-18T11:00:00",
    "sell_price_max": 66,
    "sell_price_max_date": "2022-11-18T11:00:00",
    "buy_price_min": 1,
    "buy_price_min_date": "2022-11-18T15:40:00",
    "buy_price_max": 1,
    "buy_price_max_date": "2022-11-18T15:40:00"
  },
  {
    "item_id": "T4_HIDE",
    "city": "Fort Sterling",
    "quality": 1,
    "sell_price_min": 47,
    "sell_price_min_date": "2022-11-18T16:05:00",
    "sell_price_max": 56,
    "sell_price_max_date": "2022-11-18T16:05:00",
    "buy_price_min": 0,
    "buy_price_min_date": "0001-01-01T00:00:00",
    "buy_price_max": 0,
    "buy_price_max_date": "0001-01-01T00:00:00"
  },
  {
    "item_id": "T4_HIDE",
    "city": "Martlock",
    "quality": 1,
    "sell_price_min": 56,
    "sell_price_min_date": "2022-11-18T14:35:00",
    "sell_price_max": 60,
    "sell_price_max_date": "2022-11-18T14:35:00",
    "buy_price_min": 1,
    "buy_price_min_date": "2022-11-18T06:10:00",
    "buy_price_max": 54,
    "buy_price_max_date": "2022-11-18T06:10:00"
  },
  {
    "item_id": "T5_HIDE",
    "city": "Fort Sterling",
    "quality": 1,
    "sell_price_min": 282,
    "sell_price_min_date": "2022-11-18T12:55:00",
    "sell_price_max": 304,
    "sell_price_max_date": "2022-11-18T12:55:00",
    "buy_price_min": 266,
    "buy_price_min_date": "2022-11-18T14:50:00",
    "buy_price_max": 266,
    "buy_price_max_date": "2022-11-18T14:50:00"
  },
  {
    "item_id": "T5_HIDE",
    "city": "Martlock",
    "quality": 1,
    "sell_price_min": 340,
    "sell_price_min_date": "2022-11-17T20:25:00",
    "sell_price_max": 407,
    "sell_price_max_date": "2022-11-17T20:25:00",
    "buy_price_min": 338,
    "buy_price_min_date": "2022-11-17T18:40:00",
    "buy_price_max": 338,
    "buy_price_max_date": "2022-11-17T18:40:00"
  },
  {
    "item_id": "T5_LEATHER",
    "city": "Fort Sterling",
    "quality": 1,
    "sell_price_min": 817,
    "sell_price_min_date": "2022-11-18T12:55:00",
    "sell_price_max": 882,
    "sell_price_max_date": "2022-11-18T12:55:00",
    "buy_price_min": 20,
    "buy_price_min_date": "2022-11-18T12:55:00",
    "buy_price_max": 811,
    "buy_price_max_date": "2022-11-18T12:55:00"
  },
  {
    "item_id": "T5_LEATHER",
    "city": "Martlock",
    "quality": 1,
    "sell_price_min": 777,
    "sell_price_min_date": "2022-11-18T09:15:00",
    "sell_price_max": 820,
    "sell_price_max_date": "2022-11-18T09:15:00",
    "buy_price_min": 1,
    "buy_price_min_date": "2022-11-18T09:15:00",
    "buy_price_max": 729,
    "buy_price_max_date": "2022-11-18T09:15:00"
  }
]
